{
  "floors": [
    {
      "id": "4ef8c4fe-f801-4634-ad2a-075881197b84",
      "name": "piso 1",
      "parkingSpaces": [
        {
          "id": "3bf105b8-44f7-4277-949b-5788de797123",
          "name": "vaga 1",
          "status": "vague",
          "registers": []
        },
        {
          "id": "b2dbd8bb-7774-4793-ada2-43b803007c72",
          "name": "vaga 2",
          "status": "vague",
          "registers": []
        },
        {
          "id": "6c5c55cc-377d-477d-bf19-b93983ca514a",
          "name": "vaga 3",
          "status": "vague",
          "registers": []
        },
        {
          "id": "2927f47d-7ba8-4031-9cb2-7739a72b9e77",
          "name": "vaga 4",
          "status": "filled",
          "registers": []
        },
        {
          "id": "8ddc92cb-a031-4b2f-835b-6af7952c4f58",
          "name": "vaga 5",
          "status": "vague",
          "registers": []
        }
      ]
    },
    {
      "id": "7ca95b3b-12a4-4e56-8810-4deb3c97a80b",
      "name": "piso 2",
      "parkingSpaces": [
        {
          "id": "5ebe6eef-d676-443a-9e73-0ae405d4a7b8",
          "name": "vaga 1",
          "status": "filled",
          "registers": [
            {
              "id": "fde37dde-4c84-4926-b54c-02eb2b8872d0",
              "vehicle": {
                "id": "a0a17426-60ea-454c-b269-b6d8c81b8580",
                "plate": "AAA2A1"
              },
              "entryTime": "2022-11-12T05:20:33",
              "departureTime": "2022-11-12T09:20:33"
            },
            {
              "id": "80b853cf-20c1-4190-81d4-978b32f5bb2f",
              "vehicle": {
                "id": "7e616d61-7fce-4b21-8c9e-31d86cb28875",
                "plate": "AAA2A1"
              },
              "entryTime": "2019-05-09T11:05:55",
              "departureTime": "2019-05-09T17:05:55"
            }
          ]
        },
        {
          "id": "b441d2ce-fa34-4cca-a385-400e5470a41a",
          "name": "vaga 2",
          "status": "filled",
          "registers": [
            {
              "id": "395660c7-0b87-43d2-a766-b91f83ba6d89",
              "vehicle": {
                "id": "6258f58c-f9bb-49cc-9735-b2eeeca250be",
                "plate": "AAA2A2"
              },
              "entryTime": "2022-05-21T12:45:44",
              "departureTime": "2022-05-21T21:45:44"
            },
            {
              "id": "13f3e57a-8f70-4116-b561-c53c363eae10",
              "vehicle": {
                "id": "029125ee-77b1-422d-bccf-b1dee66a3b14",
                "plate": "AAA2A2"
              },
              "entryTime": "2021-01-07T14:55:37",
              "departureTime": "2021-01-07T22:55:37"
            }
          ]
        },
        {
          "id": "9abb6767-e1d8-4402-bccf-2603fb845d82",
          "name": "vaga 3",
          "status": "filled",
          "registers": [
            {
              "id": "21cf42e9-177a-490c-97f2-33365054655b",
              "vehicle": {
                "id": "6027068a-2105-4bc3-ac30-ac555bfb89c7",
                "plate": "AAA2A3"
              },
              "entryTime": "2020-12-15T22:07:45",
              "departureTime": "2020-12-16T03:07:45"
            },
            {
              "id": "031d925b-7eea-47d5-aa69-4de467e7e5a0",
              "vehicle": {
                "id": "3397fc4c-5fa3-464f-ad09-a9a4f0bc7998",
                "plate": "AAA2A3"
              },
              "entryTime": "2022-05-11T20:45:26",
              "departureTime": "2022-05-11T22:45:26"
            }
          ]
        },
        {
          "id": "9e7a6f4c-49a2-4dbf-8cf2-67ab08215367",
          "name": "vaga 4",
          "status": "filled",
          "registers": [
            {
              "id": "94dd0b52-c68f-4ac3-bb42-0b1b109fea74",
              "vehicle": {
                "id": "282bee14-d86c-4d0b-b41b-929c4fe8e80f",
                "plate": "AAA2A4"
              },
              "entryTime": "2021-12-25T21:41:13",
              "departureTime": "2021-12-26T01:41:13"
            }
          ]
        },
        {
          "id": "20b6eaf5-1c43-463e-8b8e-c1e8a71842e9",
          "name": "vaga 5",
          "status": "vague",
          "registers": []
        }
      ]
    }
  ]
}
